{"nodes": [{"id": "riper_5_system", "label": "RIPER-5 Spec-Driven Development System", "file_type": "concept", "source_file": "process/development-protocols/orchestration.md"}, {"id": "orchestration_protocol", "label": "Orchestration Protocol", "file_type": "protocol", "source_file": "process/development-protocols/orchestration.md", "source_location": null, "source_url": null, "captured_at": null, "author": null, "contributor": null}], "edges": [{"source": "orchestration_protocol", "target": "phase_programs_protocol", "relation": "references", "confidence": "EXTRACTED", "confidence_score": 1.0, "source_file": "process/development-protocols/orchestration.md"}, {"source": "orchestration_protocol", "target": "plan_lifecycle_protocol", "relation": "references", "confidence": "EXTRACTED", "confidence_score": 1.0, "source_file": "process/development-protocols/orchestration.md"}, {"source": "orchestration_protocol", "target": "vc_autoresearch_skill", "relation": "calls", "confidence": "EXTRACTED", "confidence_score": 1.0, "source_file": "process/development-protocols/orchestration.md"}, {"source": "orchestration_protocol", "target": "vc_tester", "relation": "calls", "confidence": "EXTRACTED", "confidence_score": 1.0, "source_file": "process/development-protocols/orchestration.md"}, {"source": "orchestration_protocol", "target": "vc_execute_agent", "relation": "calls", "confidence": "EXTRACTED", "confidence_score": 1.0, "source_file": "process/development-protocols/orchestration.md"}], "hyperedges": [{"id": "riper_5_workflow", "label": "RIPER-5 Core Workflow", "nodes": ["vc_research_agent_md", "vc_spec_agent_md", "vc_plan_agent_md", "vc_validate_agent_md", "vc_update_process_agent_md"], "relation": "form", "confidence": "EXTRACTED", "confidence_score": 1.0, "source_file": "process/development-protocols/orchestration.md"}, {"id": "pvl_evl_loops", "label": "PVL and EVL Loops", "nodes": ["vc_autoresearch_skill", "vc_validate_agent", "vc_plan_agent", "vc_execute_agent", "vc_tester"], "relation": "participate_in", "confidence": "EXTRACTED", "confidence_score": 1.0, "source_file": "process/development-protocols/orchestration.md"}]}